kolektor_mcp/__init__.py
kolektor_mcp/__version__.py
kolektor_mcp/ifc_session.py
kolektor_mcp/main.py
kolektor_mcp/tools.py
kolektor_mcp/core/__init__.py
kolektor_mcp-0.1.2.dist-info/METADATA
kolektor_mcp-0.1.2.dist-info/WHEEL
kolektor_mcp-0.1.2.dist-info/entry_points.txt
kolektor_mcp-0.1.2.dist-info/top_level.txt
kolektor_mcp-0.1.2.dist-info/RECORD
