Metadata-Version: 2.4
Name: kolektor-mcp
Version: 0.1.2
Summary: Secure IFC processing MCP server for Claude Desktop
Author: Kolektor Development Team
License: Proprietary
Keywords: ifc,bim,mcp,claude
Classifier: Development Status :: 3 - Alpha
Classifier: Intended Audience :: Developers
Classifier: License :: Other/Proprietary License
Classifier: Operating System :: OS Independent
Classifier: Programming Language :: Python :: 3
Classifier: Programming Language :: Python :: 3.10
Classifier: Programming Language :: Python :: 3.11
Classifier: Programming Language :: Python :: 3.12
Classifier: Programming Language :: Cython
Classifier: Topic :: Software Development :: Libraries
Requires-Python: >=3.10
Requires-Dist: fastmcp>=2.5.1
Requires-Dist: ifcopenshell>=0.8.0
Dynamic: requires-python
